{
  "image_path": "dataset\\Focus_3_-_Student_book_-_2020\\images\\page_154.png",
  "image_size": {
    "width": 2481,
    "height": 3509
  },
  "tokens": [
    "GRAMMAR",
    "AND",
    "USE",
    "OF",
    "ENGLISH",
    "0",
    "2",
    "Will",
    "and",
    "Bill",
    "are",
    "neighbours.",
    "Rewrite",
    "the",
    "sentences",
    "for",
    "8.5",
    "Have",
    "something",
    "done",
    "an",
    "Will",
    "with",
    "have",
    "something",
    "done.",
    "We",
    "use",
    "have",
    "+",
    "object",
    "+",
    "Past",
    "Participle",
    "to",
    "talk",
    "about",
    "things",
    "1",
    "Bill",
    "cuts",
    "his",
    "grass",
    "twice",
    "a",
    "week.",
    "that",
    "we",
    "don't",
    "do",
    "ourselves",
    "but",
    "arrange",
    "for",
    "someone",
    "else",
    "Will",
    "(usually",
    "a",
    "professional)",
    "to",
    "do",
    "for",
    "us.",
    "twice",
    "a",
    "week.",
    "2",
    "After",
    "the",
    "storm",
    "last",
    "week",
    "Bill",
    "repaired",
    "his",
    "roof.",
    "After",
    "the",
    "storm",
    "last",
    "week",
    "Will",
    ".",
    "3",
    "Bill",
    "is",
    "going",
    "to",
    "change",
    "his",
    "locks",
    "because",
    "of",
    "burglaries",
    "in",
    "the",
    "area.",
    "Present",
    "Are",
    "you",
    "having",
    "the",
    "locks",
    "changed?",
    "Will",
    "because",
    "of",
    "Continuous",
    "=",
    "(by",
    "a",
    "locksmith)",
    "Present",
    "|",
    "have",
    "my",
    "house",
    "cleaned",
    "every",
    "Friday.",
    "Simple",
    "(by",
    "a",
    "professional",
    "cleaner)",
    "burglaries",
    "in",
    "the",
    "area.",
    "Past",
    "Simple",
    "We",
    "had",
    "the",
    "kitchen",
    "painted.",
    "4",
    "At",
    "10",
    "a.m.",
    "Bill",
    "was",
    "painting",
    "his",
    "garden",
    "wall.",
    "(by",
    "a",
    "professional",
    "painter)",
    "At",
    "10",
    "a.m.",
    "Will",
    "5",
    "Bill",
    "has",
    "just",
    "planted",
    "some",
    "apple",
    "trees.",
    "Will",
    ".",
    "6",
    "Bill",
    "is",
    "building",
    "a",
    "tree",
    "house",
    "for",
    "his",
    "children.",
    "Will",
    "for",
    "his",
    "children.",
    "Present",
    "They",
    "have",
    "just",
    "had",
    "a",
    "pool",
    "installed",
    "in",
    "the",
    "7",
    "Bill",
    "will",
    "walk",
    "his",
    "dog",
    "in",
    "the",
    "afternoon.",
    "Perfect",
    "garden.",
    "Will",
    "(by",
    "a",
    "professional)",
    "Past",
    "Last",
    "week",
    "Jack",
    "was",
    "having",
    "his",
    "bathroom",
    "Continuous",
    "remodelled.",
    "(by",
    "a",
    "specialist)",
    "in",
    "the",
    "afternoon.",
    "8",
    "At",
    "4",
    "p.m.",
    "Bill",
    "was",
    "washing",
    "his",
    "windows.",
    "will",
    "When",
    "will",
    "Helen",
    "have",
    "the",
    "paintings",
    "hung",
    "in",
    "her",
    "At",
    "4",
    "p.m.",
    "Will",
    "flat?",
    "9",
    "Bill",
    "cleans",
    "his",
    "carpets",
    "once",
    "a",
    "month.",
    "(by",
    "a",
    "specialist)",
    "Will",
    "once",
    "a",
    "month.",
    "be",
    "going",
    "to",
    "When",
    "are",
    "you",
    "going",
    "to",
    "have",
    "a",
    "garage",
    "built?",
    "Complete",
    "the",
    "sentences",
    "with",
    "the",
    "correct",
    "form",
    "of",
    "the",
    "(by",
    "professionals)",
    "words",
    "in",
    "brackets.",
    "Use",
    "have",
    "something",
    "done",
    "where",
    "necessary.",
    "We",
    "will",
    "redecorate",
    "our",
    "flat",
    "next",
    "year.",
    "(we",
    "will",
    "do",
    "it",
    "ourselves)",
    "1",
    "a",
    "Susan",
    "is",
    "a",
    "hairdresser.",
    "She",
    "(cut/people’s",
    "hair)",
    "for",
    "money.",
    "b",
    "I'm",
    "afraid",
    "you",
    "can’t",
    "see",
    "Joan",
    "yet.",
    "She’s",
    "in",
    "her",
    "room",
    "We",
    "will",
    "have",
    "our",
    "flat",
    "redecorated",
    "next",
    "year.",
    "(by",
    "specialists)",
    "We",
    "can",
    "use",
    "get",
    "instead",
    "of",
    "have:",
    "We",
    "had",
    "new",
    "windows",
    "fitted.",
    "=",
    "We",
    "got",
    "new",
    "windows",
    "fitted.",
    "with",
    "her",
    "hairdresser",
    "—",
    "she",
    "(style/her",
    "hair).",
    "c",
    "When",
    "|",
    "was",
    "a",
    "little",
    "kid,",
    "|",
    "once",
    "(cut/my",
    "hair)",
    "myself.",
    "1",
    "Complete",
    "the",
    "sentences",
    "with",
    "the",
    "correct",
    "form",
    "of",
    "have.",
    "1",
    "Last",
    "weekend",
    "|",
    "my",
    "bike",
    "repaired,",
    "so",
    "2",
    "a",
    "Excuse",
    "me,",
    "could",
    "you",
    "|",
    "couldn't",
    "go",
    "for",
    "a",
    "bike",
    "ride.",
    "(take/a",
    "photo)",
    "of",
    "us,",
    "please?",
    "2A:",
    "you",
    "your",
    "wedding",
    "b",
    "|",
    "need",
    "to",
    "(take/a",
    "photo)",
    "organised?",
    "for",
    "my",
    "new",
    "passport.",
    "B:",
    "Yes,",
    "we",
    "are.",
    "We're",
    "too",
    "busy",
    "to",
    "do",
    "it",
    "on",
    "our",
    "own.",
    "c",
    "You",
    "have",
    "to",
    "pay",
    "ten",
    "euros",
    "if",
    "you",
    "want",
    "to",
    "3",
    "Aunt",
    "Sophie",
    "is",
    "eighty",
    "years",
    "old",
    "and",
    "she",
    "doesn’t",
    "cook",
    "(take/photos)",
    "inside",
    "the",
    "any",
    "more.",
    "She",
    "her",
    "meals",
    "delivered",
    "museum.",
    "every",
    "day.",
    "3",
    "a",
    "|'m",
    "using",
    "public",
    "transport",
    "this",
    "week",
    "because",
    "my",
    "car",
    "4",
    "The",
    "windows",
    "look",
    "really",
    "shiny!",
    "you",
    "is",
    "at",
    "the",
    "mechanic’s.",
    "|",
    "(it/repair).",
    "them",
    "cleaned",
    "recently?",
    "b",
    "Tom’s",
    "a",
    "mechanic.",
    "He",
    "(repair/cars).",
    "5",
    "A:",
    "Where",
    "did",
    "you",
    "buy",
    "your",
    "new",
    "wooden",
    "furniture?",
    "B:",
    "|",
    "it",
    "designed",
    "and",
    "made",
    "by",
    "a",
    "carpenter.",
    ";",
    "c",
    "We",
    "can",
    "(repair/your",
    "car)",
    "at",
    "our",
    "garage.",
    "Here",
    "are",
    "our",
    "prices.",
    "6",
    "Hi",
    "Sandra.",
    "Sorry,",
    "can",
    "|",
    "call",
    "you",
    "back",
    "later?",
    "|",
    "my",
    "portrait",
    "painted",
    "at",
    "the",
    "moment.",
    ";",
    "yp",
    "P",
    "4a",
    "Tomis",
    "a",
    "travel",
    "agent.",
    "He",
    "(book/holidays)",
    "for",
    "other",
    "people.",
    "7",
    "|",
    "think",
    "it's",
    "best",
    "if",
    "we",
    "meet",
    "at",
    "your",
    "place.",
    "We",
    "the",
    "bathroom",
    "redecorated",
    "and",
    "there’s",
    "b",
    "Last",
    "year,",
    "we",
    "(book/our",
    "holiday)",
    "by",
    "a",
    "travel",
    "agent.",
    "dust",
    "everywhere.",
    "8",
    "Of",
    "course",
    "Samantha's",
    "dress",
    "was",
    "expensive!",
    "She",
    "¢",
    "I'm",
    "online",
    "right",
    "now",
    "and",
    "|",
    "it",
    "made",
    "specially",
    "for",
    "the",
    "party.",
    "(book/my",
    "holiday).",
    "5",
    "a",
    "These",
    "wooden",
    "floors",
    "look",
    "old.",
    "Mum",
    "(all",
    "of",
    "them/clean)",
    "by",
    "a",
    "professional",
    "at",
    "the",
    "moment.",
    "b",
    "|",
    "was",
    "exhausted",
    "because",
    "|",
    "(clean/all",
    "the",
    "floors)",
    "on",
    "my",
    "own.",
    "c",
    "If",
    "you",
    "use",
    "this",
    "product,",
    "you",
    "(clean/all",
    "your",
    "floors)",
    "really",
    "well.",
    "154"
  ],
  "bboxes": [
    [
      70,
      24,
      221,
      40
    ],
    [
      230,
      25,
      294,
      39
    ],
    [
      305,
      24,
      356,
      40
    ],
    [
      367,
      24,
      405,
      40
    ],
    [
      416,
      24,
      536,
      40
    ],
    [
      264,
      80,
      267,
      82
    ],
    [
      524,
      75,
      532,
      83
    ],
    [
      549,
      75,
      574,
      83
    ],
    [
      580,
      75,
      604,
      83
    ],
    [
      611,
      75,
      629,
      83
    ],
    [
      635,
      78,
      656,
      83
    ],
    [
      662,
      75,
      742,
      86
    ],
    [
      748,
      76,
      800,
      83
    ],
    [
      805,
      75,
      827,
      83
    ],
    [
      833,
      76,
      900,
      83
    ],
    [
      905,
      75,
      925,
      83
    ],
    [
      93,
      80,
      120,
      90
    ],
    [
      142,
      80,
      187,
      90
    ],
    [
      194,
      80,
      290,
      94
    ],
    [
      297,
      80,
      343,
      90
    ],
    [
      564,
      89,
      594,
      90
    ],
    [
      549,
      88,
      574,
      96
    ],
    [
      580,
      88,
      608,
      97
    ],
    [
      614,
      88,
      646,
      97
    ],
    [
      651,
      88,
      723,
      99
    ],
    [
      729,
      88,
      766,
      97
    ],
    [
      91,
      104,
      113,
      111
    ],
    [
      118,
      106,
      139,
      111
    ],
    [
      145,
      103,
      176,
      111
    ],
    [
      182,
      105,
      190,
      111
    ],
    [
      195,
      103,
      238,
      114
    ],
    [
      244,
      105,
      252,
      111
    ],
    [
      258,
      104,
      286,
      111
    ],
    [
      292,
      103,
      355,
      114
    ],
    [
      359,
      105,
      372,
      111
    ],
    [
      377,
      103,
      400,
      111
    ],
    [
      405,
      103,
      442,
      111
    ],
    [
      446,
      103,
      486,
      114
    ],
    [
      550,
      106,
      555,
      113
    ],
    [
      567,
      105,
      584,
      113
    ],
    [
      590,
      107,
      615,
      113
    ],
    [
      620,
      105,
      637,
      113
    ],
    [
      642,
      108,
      675,
      115
    ],
    [
      679,
      106,
      713,
      113
    ],
    [
      718,
      108,
      724,
      113
    ],
    [
      729,
      105,
      765,
      113
    ],
    [
      92,
      117,
      117,
      125
    ],
    [
      121,
      119,
      139,
      125
    ],
    [
      144,
      117,
      178,
      125
    ],
    [
      182,
      117,
      199,
      125
    ],
    [
      204,
      117,
      264,
      125
    ],
    [
      269,
      117,
      290,
      125
    ],
    [
      295,
      119,
      344,
      127
    ],
    [
      349,
      117,
      367,
      125
    ],
    [
      371,
      119,
      431,
      125
    ],
    [
      436,
      117,
      461,
      125
    ],
    [
      552,
      120,
      575,
      128
    ],
    [
      92,
      130,
      139,
      141
    ],
    [
      144,
      133,
      150,
      138
    ],
    [
      156,
      130,
      237,
      141
    ],
    [
      242,
      132,
      255,
      138
    ],
    [
      260,
      130,
      276,
      138
    ],
    [
      281,
      130,
      299,
      138
    ],
    [
      304,
      133,
      320,
      138
    ],
    [
      760,
      121,
      794,
      128
    ],
    [
      799,
      123,
      805,
      128
    ],
    [
      810,
      120,
      846,
      128
    ],
    [
      552,
      134,
      559,
      141
    ],
    [
      567,
      133,
      599,
      142
    ],
    [
      603,
      133,
      623,
      142
    ],
    [
      629,
      135,
      664,
      142
    ],
    [
      671,
      133,
      691,
      142
    ],
    [
      696,
      133,
      729,
      142
    ],
    [
      735,
      133,
      752,
      141
    ],
    [
      758,
      133,
      812,
      144
    ],
    [
      818,
      133,
      834,
      142
    ],
    [
      839,
      133,
      868,
      142
    ],
    [
      563,
      148,
      595,
      156
    ],
    [
      599,
      148,
      619,
      156
    ],
    [
      624,
      149,
      659,
      156
    ],
    [
      665,
      148,
      686,
      156
    ],
    [
      690,
      148,
      723,
      156
    ],
    [
      727,
      148,
      750,
      156
    ],
    [
      916,
      155,
      918,
      156
    ],
    [
      548,
      162,
      555,
      169
    ],
    [
      564,
      161,
      582,
      169
    ],
    [
      588,
      162,
      596,
      169
    ],
    [
      601,
      162,
      638,
      172
    ],
    [
      643,
      163,
      656,
      169
    ],
    [
      661,
      161,
      708,
      172
    ],
    [
      714,
      161,
      730,
      169
    ],
    [
      736,
      161,
      767,
      169
    ],
    [
      772,
      161,
      825,
      169
    ],
    [
      831,
      161,
      843,
      169
    ],
    [
      848,
      161,
      911,
      172
    ],
    [
      566,
      176,
      576,
      183
    ],
    [
      581,
      175,
      601,
      183
    ],
    [
      607,
      178,
      637,
      183
    ],
    [
      101,
      187,
      149,
      195
    ],
    [
      191,
      187,
      214,
      195
    ],
    [
      217,
      190,
      239,
      197
    ],
    [
      244,
      187,
      286,
      197
    ],
    [
      291,
      187,
      311,
      195
    ],
    [
      316,
      187,
      347,
      195
    ],
    [
      351,
      187,
      412,
      197
    ],
    [
      569,
      186,
      594,
      198
    ],
    [
      783,
      189,
      836,
      197
    ],
    [
      841,
      189,
      854,
      197
    ],
    [
      100,
      200,
      173,
      208
    ],
    [
      180,
      199,
      185,
      211
    ],
    [
      192,
      200,
      209,
      210
    ],
    [
      214,
      202,
      220,
      208
    ],
    [
      225,
      200,
      284,
      209
    ],
    [
      101,
      154,
      149,
      161
    ],
    [
      192,
      154,
      195,
      161
    ],
    [
      199,
      154,
      228,
      161
    ],
    [
      233,
      156,
      252,
      163
    ],
    [
      257,
      154,
      294,
      161
    ],
    [
      299,
      154,
      348,
      161
    ],
    [
      352,
      156,
      384,
      163
    ],
    [
      389,
      154,
      428,
      163
    ],
    [
      100,
      165,
      143,
      177
    ],
    [
      192,
      166,
      209,
      176
    ],
    [
      214,
      169,
      220,
      174
    ],
    [
      225,
      166,
      297,
      177
    ],
    [
      302,
      166,
      349,
      175
    ],
    [
      570,
      204,
      634,
      214
    ],
    [
      639,
      204,
      649,
      212
    ],
    [
      654,
      204,
      674,
      212
    ],
    [
      680,
      207,
      710,
      212
    ],
    [
      101,
      221,
      127,
      228
    ],
    [
      132,
      220,
      175,
      230
    ],
    [
      193,
      221,
      211,
      228
    ],
    [
      216,
      220,
      239,
      228
    ],
    [
      244,
      220,
      264,
      228
    ],
    [
      269,
      220,
      314,
      228
    ],
    [
      319,
      220,
      370,
      230
    ],
    [
      550,
      218,
      558,
      225
    ],
    [
      565,
      218,
      580,
      225
    ],
    [
      586,
      218,
      599,
      225
    ],
    [
      604,
      220,
      630,
      225
    ],
    [
      636,
      217,
      654,
      225
    ],
    [
      659,
      220,
      682,
      225
    ],
    [
      688,
      218,
      740,
      227
    ],
    [
      746,
      217,
      762,
      225
    ],
    [
      768,
      217,
      812,
      227
    ],
    [
      818,
      217,
      845,
      225
    ],
    [
      192,
      233,
      209,
      243
    ],
    [
      214,
      236,
      220,
      241
    ],
    [
      225,
      233,
      297,
      243
    ],
    [
      302,
      233,
      347,
      243
    ],
    [
      560,
      232,
      574,
      240
    ],
    [
      580,
      232,
      593,
      240
    ],
    [
      598,
      235,
      624,
      240
    ],
    [
      629,
      232,
      652,
      240
    ],
    [
      549,
      246,
      556,
      253
    ],
    [
      565,
      245,
      583,
      253
    ],
    [
      591,
      245,
      608,
      253
    ],
    [
      614,
      246,
      637,
      256
    ],
    [
      642,
      245,
      690,
      256
    ],
    [
      696,
      248,
      730,
      253
    ],
    [
      736,
      245,
      772,
      256
    ],
    [
      776,
      247,
      811,
      253
    ],
    [
      560,
      259,
      585,
      272
    ],
    [
      811,
      268,
      813,
      269
    ],
    [
      550,
      275,
      558,
      282
    ],
    [
      567,
      274,
      584,
      282
    ],
    [
      590,
      275,
      598,
      282
    ],
    [
      604,
      274,
      656,
      285
    ],
    [
      661,
      277,
      667,
      282
    ],
    [
      672,
      276,
      697,
      282
    ],
    [
      703,
      274,
      741,
      282
    ],
    [
      746,
      274,
      763,
      282
    ],
    [
      769,
      274,
      785,
      282
    ],
    [
      790,
      274,
      844,
      282
    ],
    [
      564,
      286,
      587,
      298
    ],
    [
      757,
      287,
      775,
      295
    ],
    [
      780,
      287,
      796,
      295
    ],
    [
      802,
      287,
      856,
      295
    ],
    [
      101,
      300,
      149,
      308
    ],
    [
      193,
      300,
      221,
      310
    ],
    [
      225,
      300,
      255,
      308
    ],
    [
      258,
      300,
      280,
      310
    ],
    [
      284,
      300,
      308,
      308
    ],
    [
      312,
      302,
      319,
      308
    ],
    [
      323,
      300,
      352,
      310
    ],
    [
      357,
      300,
      410,
      308
    ],
    [
      415,
      300,
      424,
      307
    ],
    [
      429,
      300,
      448,
      308
    ],
    [
      550,
      301,
      557,
      308
    ],
    [
      566,
      300,
      584,
      308
    ],
    [
      589,
      300,
      609,
      308
    ],
    [
      614,
      300,
      642,
      308
    ],
    [
      647,
      300,
      663,
      308
    ],
    [
      669,
      300,
      694,
      311
    ],
    [
      700,
      301,
      709,
      308
    ],
    [
      714,
      300,
      735,
      308
    ],
    [
      740,
      300,
      806,
      308
    ],
    [
      101,
      311,
      147,
      324
    ],
    [
      192,
      311,
      237,
      324
    ],
    [
      565,
      317,
      588,
      325
    ],
    [
      192,
      325,
      209,
      335
    ],
    [
      214,
      328,
      220,
      333
    ],
    [
      225,
      325,
      301,
      335
    ],
    [
      101,
      254,
      127,
      261
    ],
    [
      192,
      254,
      216,
      261
    ],
    [
      220,
      254,
      251,
      261
    ],
    [
      255,
      254,
      282,
      261
    ],
    [
      286,
      256,
      309,
      261
    ],
    [
      314,
      254,
      355,
      263
    ],
    [
      361,
      254,
      377,
      261
    ],
    [
      382,
      254,
      444,
      261
    ],
    [
      100,
      267,
      173,
      274
    ],
    [
      192,
      267,
      267,
      274
    ],
    [
      192,
      279,
      209,
      289
    ],
    [
      214,
      282,
      220,
      287
    ],
    [
      225,
      279,
      283,
      290
    ],
    [
      759,
      318,
      769,
      325
    ],
    [
      774,
      317,
      794,
      325
    ],
    [
      800,
      317,
      866,
      325
    ],
    [
      552,
      331,
      559,
      338
    ],
    [
      567,
      331,
      582,
      338
    ],
    [
      586,
      331,
      593,
      338
    ],
    [
      598,
      333,
      625,
      341
    ],
    [
      632,
      330,
      649,
      338
    ],
    [
      654,
      333,
      678,
      338
    ],
    [
      682,
      330,
      735,
      341
    ],
    [
      740,
      330,
      757,
      338
    ],
    [
      761,
      330,
      821,
      338
    ],
    [
      99,
      345,
      122,
      357
    ],
    [
      193,
      346,
      226,
      354
    ],
    [
      231,
      346,
      252,
      353
    ],
    [
      257,
      346,
      291,
      354
    ],
    [
      296,
      346,
      326,
      354
    ],
    [
      330,
      346,
      351,
      354
    ],
    [
      355,
      346,
      413,
      356
    ],
    [
      418,
      346,
      450,
      356
    ],
    [
      454,
      347,
      463,
      353
    ],
    [
      469,
      346,
      488,
      354
    ],
    [
      572,
      346,
      587,
      354
    ],
    [
      591,
      346,
      598,
      353
    ],
    [
      603,
      349,
      630,
      356
    ],
    [
      636,
      345,
      659,
      353
    ],
    [
      192,
      359,
      217,
      367
    ],
    [
      551,
      359,
      559,
      367
    ],
    [
      567,
      359,
      585,
      367
    ],
    [
      591,
      359,
      630,
      367
    ],
    [
      636,
      359,
      652,
      367
    ],
    [
      657,
      361,
      704,
      369
    ],
    [
      709,
      362,
      740,
      367
    ],
    [
      746,
      362,
      751,
      367
    ],
    [
      757,
      359,
      802,
      367
    ],
    [
      192,
      371,
      209,
      381
    ],
    [
      214,
      374,
      219,
      379
    ],
    [
      224,
      371,
      280,
      382
    ],
    [
      562,
      372,
      586,
      385
    ],
    [
      759,
      377,
      790,
      382
    ],
    [
      796,
      377,
      802,
      382
    ],
    [
      807,
      374,
      852,
      382
    ],
    [
      101,
      392,
      116,
      400
    ],
    [
      121,
      392,
      158,
      402
    ],
    [
      164,
      393,
      176,
      400
    ],
    [
      193,
      392,
      226,
      400
    ],
    [
      231,
      395,
      251,
      400
    ],
    [
      254,
      395,
      277,
      406
    ],
    [
      281,
      392,
      318,
      402
    ],
    [
      322,
      393,
      335,
      400
    ],
    [
      340,
      392,
      369,
      400
    ],
    [
      374,
      395,
      380,
      400
    ],
    [
      384,
      395,
      427,
      402
    ],
    [
      431,
      392,
      467,
      400
    ],
    [
      549,
      394,
      616,
      405
    ],
    [
      621,
      394,
      643,
      403
    ],
    [
      648,
      396,
      716,
      403
    ],
    [
      721,
      394,
      750,
      403
    ],
    [
      755,
      394,
      777,
      403
    ],
    [
      783,
      396,
      830,
      403
    ],
    [
      835,
      394,
      867,
      403
    ],
    [
      873,
      394,
      887,
      403
    ],
    [
      891,
      394,
      913,
      403
    ],
    [
      192,
      405,
      209,
      414
    ],
    [
      214,
      404,
      295,
      415
    ],
    [
      549,
      408,
      590,
      416
    ],
    [
      596,
      408,
      607,
      416
    ],
    [
      613,
      408,
      674,
      416
    ],
    [
      681,
      408,
      704,
      416
    ],
    [
      711,
      408,
      742,
      416
    ],
    [
      747,
      408,
      819,
      418
    ],
    [
      825,
      408,
      859,
      416
    ],
    [
      863,
      408,
      905,
      416
    ],
    [
      550,
      424,
      619,
      432
    ],
    [
      93,
      428,
      113,
      436
    ],
    [
      118,
      427,
      141,
      435
    ],
    [
      146,
      427,
      221,
      436
    ],
    [
      226,
      430,
      248,
      436
    ],
    [
      252,
      427,
      272,
      436
    ],
    [
      276,
      429,
      304,
      436
    ],
    [
      307,
      430,
      336,
      438
    ],
    [
      342,
      428,
      363,
      437
    ],
    [
      367,
      427,
      387,
      435
    ],
    [
      393,
      427,
      409,
      436
    ],
    [
      415,
      428,
      422,
      436
    ],
    [
      427,
      427,
      490,
      437
    ],
    [
      550,
      440,
      555,
      448
    ],
    [
      563,
      443,
      569,
      448
    ],
    [
      578,
      440,
      615,
      448
    ],
    [
      621,
      441,
      629,
      448
    ],
    [
      634,
      443,
      640,
      448
    ],
    [
      646,
      440,
      720,
      448
    ],
    [
      726,
      440,
      749,
      448
    ],
    [
      578,
      453,
      662,
      463
    ],
    [
      667,
      453,
      694,
      462
    ],
    [
      698,
      453,
      716,
      461
    ],
    [
      721,
      456,
      767,
      463
    ],
    [
      563,
      467,
      571,
      475
    ],
    [
      579,
      467,
      596,
      475
    ],
    [
      602,
      467,
      638,
      475
    ],
    [
      643,
      470,
      665,
      477
    ],
    [
      671,
      467,
      701,
      475
    ],
    [
      706,
      470,
      727,
      475
    ],
    [
      732,
      467,
      762,
      475
    ],
    [
      768,
      469,
      790,
      477
    ],
    [
      796,
      467,
      827,
      475
    ],
    [
      833,
      468,
      843,
      475
    ],
    [
      849,
      467,
      869,
      475
    ],
    [
      874,
      470,
      906,
      475
    ],
    [
      93,
      444,
      113,
      452
    ],
    [
      118,
      444,
      139,
      452
    ],
    [
      143,
      444,
      174,
      452
    ],
    [
      180,
      447,
      203,
      452
    ],
    [
      207,
      444,
      230,
      452
    ],
    [
      234,
      444,
      319,
      452
    ],
    [
      324,
      445,
      351,
      452
    ],
    [
      355,
      447,
      384,
      454
    ],
    [
      389,
      444,
      408,
      454
    ],
    [
      413,
      444,
      482,
      454
    ],
    [
      91,
      461,
      113,
      469
    ],
    [
      118,
      463,
      139,
      469
    ],
    [
      145,
      463,
      166,
      469
    ],
    [
      171,
      462,
      195,
      471
    ],
    [
      199,
      461,
      245,
      469
    ],
    [
      251,
      461,
      263,
      469
    ],
    [
      268,
      461,
      300,
      469
    ],
    [
      93,
      478,
      113,
      485
    ],
    [
      118,
      477,
      143,
      485
    ],
    [
      148,
      480,
      174,
      485
    ],
    [
      178,
      477,
      234,
      485
    ],
    [
      239,
      477,
      276,
      485
    ],
    [
      282,
      481,
      290,
      483
    ],
    [
      295,
      478,
      316,
      485
    ],
    [
      320,
      479,
      345,
      488
    ],
    [
      349,
      480,
      375,
      485
    ],
    [
      380,
      477,
      435,
      485
    ],
    [
      440,
      477,
      476,
      485
    ],
    [
      577,
      482,
      603,
      490
    ],
    [
      609,
      482,
      629,
      490
    ],
    [
      635,
      482,
      706,
      490
    ],
    [
      709,
      487,
      717,
      488
    ],
    [
      721,
      482,
      743,
      490
    ],
    [
      578,
      495,
      638,
      506
    ],
    [
      643,
      495,
      673,
      505
    ],
    [
      559,
      513,
      565,
      518
    ],
    [
      573,
      510,
      611,
      519
    ],
    [
      612,
      509,
      617,
      522
    ],
    [
      623,
      514,
      647,
      519
    ],
    [
      648,
      509,
      653,
      522
    ],
    [
      664,
      510,
      691,
      519
    ],
    [
      696,
      510,
      717,
      520
    ],
    [
      724,
      511,
      725,
      518
    ],
    [
      731,
      514,
      762,
      519
    ],
    [
      578,
      524,
      626,
      534
    ],
    [
      632,
      523,
      658,
      533
    ],
    [
      663,
      523,
      707,
      534
    ],
    [
      83,
      515,
      89,
      523
    ],
    [
      108,
      515,
      175,
      526
    ],
    [
      180,
      515,
      202,
      524
    ],
    [
      207,
      517,
      275,
      524
    ],
    [
      280,
      515,
      309,
      524
    ],
    [
      314,
      515,
      336,
      524
    ],
    [
      342,
      517,
      389,
      524
    ],
    [
      394,
      515,
      426,
      524
    ],
    [
      432,
      515,
      446,
      524
    ],
    [
      451,
      515,
      486,
      524
    ],
    [
      110,
      534,
      114,
      542
    ],
    [
      126,
      534,
      150,
      542
    ],
    [
      154,
      534,
      213,
      542
    ],
    [
      219,
      534,
      220,
      542
    ],
    [
      323,
      537,
      341,
      544
    ],
    [
      346,
      534,
      372,
      542
    ],
    [
      378,
      534,
      435,
      544
    ],
    [
      440,
      537,
      454,
      542
    ],
    [
      550,
      539,
      557,
      546
    ],
    [
      563,
      541,
      569,
      546
    ],
    [
      579,
      539,
      622,
      547
    ],
    [
      628,
      542,
      650,
      548
    ],
    [
      656,
      538,
      691,
      547
    ],
    [
      696,
      542,
      719,
      549
    ],
    [
      126,
      549,
      126,
      556
    ],
    [
      133,
      548,
      185,
      557
    ],
    [
      190,
      552,
      206,
      559
    ],
    [
      211,
      548,
      229,
      557
    ],
    [
      234,
      552,
      239,
      557
    ],
    [
      245,
      548,
      272,
      557
    ],
    [
      277,
      548,
      304,
      557
    ],
    [
      586,
      552,
      629,
      561
    ],
    [
      634,
      552,
      676,
      562
    ],
    [
      681,
      552,
      694,
      560
    ],
    [
      699,
      555,
      715,
      561
    ],
    [
      721,
      552,
      769,
      562
    ],
    [
      109,
      564,
      138,
      571
    ],
    [
      241,
      567,
      263,
      574
    ],
    [
      365,
      567,
      393,
      574
    ],
    [
      397,
      563,
      454,
      574
    ],
    [
      567,
      567,
      574,
      575
    ],
    [
      582,
      567,
      583,
      575
    ],
    [
      589,
      567,
      621,
      575
    ],
    [
      625,
      569,
      638,
      575
    ],
    [
      799,
      567,
      842,
      576
    ],
    [
      848,
      567,
      889,
      577
    ],
    [
      125,
      579,
      196,
      589
    ],
    [
      577,
      581,
      595,
      589
    ],
    [
      600,
      584,
      619,
      591
    ],
    [
      623,
      584,
      649,
      589
    ],
    [
      654,
      582,
      713,
      591
    ],
    [
      125,
      595,
      137,
      602
    ],
    [
      142,
      595,
      167,
      603
    ],
    [
      172,
      597,
      190,
      602
    ],
    [
      195,
      597,
      217,
      602
    ],
    [
      222,
      595,
      260,
      602
    ],
    [
      265,
      596,
      286,
      602
    ],
    [
      292,
      594,
      321,
      605
    ],
    [
      326,
      596,
      338,
      602
    ],
    [
      344,
      594,
      360,
      602
    ],
    [
      365,
      595,
      373,
      602
    ],
    [
      378,
      597,
      392,
      602
    ],
    [
      398,
      597,
      419,
      602
    ],
    [
      424,
      597,
      453,
      602
    ],
    [
      563,
      597,
      569,
      603
    ],
    [
      577,
      595,
      600,
      603
    ],
    [
      607,
      595,
      636,
      603
    ],
    [
      640,
      596,
      653,
      603
    ],
    [
      659,
      598,
      681,
      605
    ],
    [
      685,
      596,
      705,
      603
    ],
    [
      711,
      598,
      746,
      603
    ],
    [
      751,
      595,
      758,
      603
    ],
    [
      762,
      598,
      785,
      605
    ],
    [
      790,
      596,
      821,
      603
    ],
    [
      825,
      596,
      837,
      603
    ],
    [
      109,
      610,
      116,
      617
    ],
    [
      124,
      610,
      155,
      617
    ],
    [
      160,
      609,
      205,
      620
    ],
    [
      210,
      610,
      218,
      617
    ],
    [
      224,
      609,
      264,
      620
    ],
    [
      268,
      612,
      301,
      620
    ],
    [
      306,
      609,
      326,
      617
    ],
    [
      331,
      609,
      354,
      617
    ],
    [
      360,
      609,
      381,
      617
    ],
    [
      386,
      609,
      434,
      617
    ],
    [
      439,
      609,
      470,
      617
    ],
    [
      745,
      610,
      830,
      620
    ],
    [
      836,
      610,
      873,
      618
    ],
    [
      878,
      610,
      898,
      618
    ],
    [
      125,
      627,
      146,
      635
    ],
    [
      151,
      627,
      187,
      632
    ],
    [
      193,
      624,
      216,
      632
    ],
    [
      319,
      624,
      339,
      632
    ],
    [
      344,
      624,
      381,
      632
    ],
    [
      386,
      624,
      446,
      632
    ],
    [
      578,
      626,
      636,
      631
    ],
    [
      124,
      642,
      159,
      650
    ],
    [
      164,
      639,
      189,
      650
    ],
    [
      550,
      637,
      557,
      645
    ],
    [
      563,
      640,
      569,
      645
    ],
    [
      579,
      637,
      596,
      645
    ],
    [
      602,
      638,
      636,
      647
    ],
    [
      642,
      637,
      681,
      647
    ],
    [
      685,
      638,
      744,
      647
    ],
    [
      748,
      637,
      771,
      645
    ],
    [
      775,
      637,
      809,
      645
    ],
    [
      814,
      637,
      867,
      645
    ],
    [
      873,
      640,
      891,
      647
    ],
    [
      896,
      640,
      914,
      645
    ],
    [
      109,
      655,
      116,
      662
    ],
    [
      124,
      654,
      148,
      663
    ],
    [
      153,
      654,
      209,
      663
    ],
    [
      215,
      654,
      241,
      663
    ],
    [
      246,
      654,
      280,
      665
    ],
    [
      284,
      654,
      320,
      665
    ],
    [
      424,
      658,
      446,
      665
    ],
    [
      578,
      653,
      587,
      660
    ],
    [
      592,
      654,
      603,
      660
    ],
    [
      608,
      652,
      628,
      660
    ],
    [
      634,
      652,
      708,
      660
    ],
    [
      715,
      652,
      716,
      660
    ],
    [
      578,
      666,
      640,
      676
    ],
    [
      221,
      669,
      254,
      678
    ],
    [
      259,
      669,
      310,
      678
    ],
    [
      316,
      669,
      372,
      680
    ],
    [
      559,
      680,
      567,
      688
    ],
    [
      573,
      681,
      612,
      689
    ],
    [
      617,
      683,
      623,
      689
    ],
    [
      629,
      680,
      694,
      689
    ],
    [
      700,
      681,
      717,
      689
    ],
    [
      578,
      694,
      657,
      704
    ],
    [
      109,
      685,
      116,
      692
    ],
    [
      124,
      685,
      138,
      692
    ],
    [
      143,
      684,
      185,
      693
    ],
    [
      191,
      684,
      211,
      693
    ],
    [
      216,
      687,
      238,
      695
    ],
    [
      244,
      684,
      267,
      695
    ],
    [
      271,
      687,
      300,
      695
    ],
    [
      305,
      687,
      330,
      693
    ],
    [
      334,
      684,
      386,
      693
    ],
    [
      392,
      684,
      453,
      693
    ],
    [
      120,
      701,
      132,
      708
    ],
    [
      138,
      701,
      139,
      708
    ],
    [
      247,
      700,
      255,
      708
    ],
    [
      259,
      699,
      319,
      710
    ],
    [
      325,
      699,
      348,
      708
    ],
    [
      354,
      699,
      390,
      708
    ],
    [
      395,
      699,
      410,
      710
    ],
    [
      415,
      703,
      421,
      708
    ],
    [
      426,
      701,
      490,
      710
    ],
    [
      829,
      710,
      831,
      711
    ],
    [
      559,
      712,
      565,
      717
    ],
    [
      573,
      709,
      594,
      717
    ],
    [
      600,
      712,
      621,
      717
    ],
    [
      795,
      709,
      871,
      719
    ],
    [
      875,
      709,
      897,
      719
    ],
    [
      578,
      723,
      590,
      730
    ],
    [
      594,
      725,
      615,
      730
    ],
    [
      620,
      725,
      669,
      732
    ],
    [
      675,
      722,
      705,
      730
    ],
    [
      711,
      725,
      729,
      730
    ],
    [
      735,
      725,
      756,
      730
    ],
    [
      761,
      722,
      802,
      732
    ],
    [
      109,
      715,
      116,
      722
    ],
    [
      126,
      715,
      137,
      722
    ],
    [
      143,
      715,
      191,
      723
    ],
    [
      196,
      715,
      232,
      725
    ],
    [
      238,
      718,
      259,
      723
    ],
    [
      265,
      715,
      266,
      722
    ],
    [
      272,
      715,
      292,
      723
    ],
    [
      297,
      718,
      320,
      725
    ],
    [
      326,
      715,
      355,
      723
    ],
    [
      361,
      715,
      395,
      723
    ],
    [
      126,
      730,
      126,
      737
    ],
    [
      228,
      732,
      238,
      737
    ],
    [
      259,
      730,
      298,
      738
    ],
    [
      312,
      729,
      352,
      738
    ],
    [
      357,
      731,
      369,
      738
    ],
    [
      373,
      729,
      394,
      738
    ],
    [
      399,
      731,
      456,
      738
    ],
    [
      612,
      738,
      613,
      738
    ],
    [
      132,
      732,
      258,
      740
    ],
    [
      303,
      732,
      311,
      740
    ],
    [
      550,
      737,
      569,
      745
    ],
    [
      577,
      737,
      620,
      745
    ],
    [
      625,
      740,
      632,
      745
    ],
    [
      636,
      737,
      671,
      745
    ],
    [
      677,
      738,
      717,
      747
    ],
    [
      723,
      737,
      740,
      745
    ],
    [
      600,
      750,
      700,
      761
    ],
    [
      704,
      750,
      722,
      758
    ],
    [
      727,
      750,
      761,
      758
    ],
    [
      766,
      750,
      814,
      761
    ],
    [
      109,
      745,
      116,
      752
    ],
    [
      126,
      745,
      126,
      752
    ],
    [
      132,
      744,
      164,
      753
    ],
    [
      169,
      745,
      184,
      753
    ],
    [
      189,
      744,
      216,
      753
    ],
    [
      222,
      744,
      229,
      752
    ],
    [
      232,
      748,
      250,
      753
    ],
    [
      256,
      746,
      288,
      753
    ],
    [
      293,
      746,
      305,
      753
    ],
    [
      309,
      748,
      338,
      755
    ],
    [
      343,
      744,
      380,
      755
    ],
    [
      385,
      745,
      406,
      753
    ],
    [
      219,
      760,
      240,
      768
    ],
    [
      245,
      760,
      308,
      768
    ],
    [
      314,
      760,
      393,
      768
    ],
    [
      399,
      760,
      422,
      768
    ],
    [
      427,
      760,
      470,
      768
    ],
    [
      564,
      765,
      572,
      773
    ],
    [
      579,
      766,
      604,
      773
    ],
    [
      608,
      768,
      638,
      776
    ],
    [
      644,
      768,
      661,
      773
    ],
    [
      833,
      765,
      897,
      774
    ],
    [
      585,
      779,
      634,
      789
    ],
    [
      640,
      779,
      654,
      789
    ],
    [
      659,
      782,
      665,
      787
    ],
    [
      670,
      779,
      705,
      787
    ],
    [
      711,
      781,
      751,
      789
    ],
    [
      125,
      775,
      152,
      783
    ],
    [
      157,
      775,
      234,
      785
    ],
    [
      109,
      791,
      116,
      798
    ],
    [
      125,
      790,
      141,
      798
    ],
    [
      145,
      793,
      187,
      798
    ],
    [
      193,
      790,
      265,
      798
    ],
    [
      270,
      790,
      303,
      798
    ],
    [
      308,
      793,
      332,
      798
    ],
    [
      336,
      791,
      405,
      801
    ],
    [
      412,
      790,
      435,
      798
    ],
    [
      563,
      797,
      569,
      802
    ],
    [
      578,
      795,
      596,
      802
    ],
    [
      602,
      794,
      640,
      802
    ],
    [
      646,
      794,
      675,
      805
    ],
    [
      681,
      797,
      706,
      802
    ],
    [
      712,
      794,
      735,
      802
    ],
    [
      741,
      795,
      742,
      802
    ],
    [
      222,
      806,
      229,
      813
    ],
    [
      234,
      805,
      270,
      813
    ],
    [
      275,
      805,
      330,
      815
    ],
    [
      334,
      805,
      352,
      813
    ],
    [
      356,
      805,
      377,
      813
    ],
    [
      382,
      807,
      417,
      815
    ],
    [
      578,
      807,
      640,
      818
    ],
    [
      645,
      807,
      698,
      818
    ],
    [
      550,
      821,
      557,
      829
    ],
    [
      563,
      823,
      569,
      829
    ],
    [
      577,
      821,
      616,
      829
    ],
    [
      621,
      821,
      673,
      829
    ],
    [
      678,
      821,
      714,
      829
    ],
    [
      719,
      821,
      746,
      829
    ],
    [
      751,
      821,
      774,
      829
    ],
    [
      780,
      821,
      812,
      829
    ],
    [
      757,
      836,
      773,
      845
    ],
    [
      779,
      836,
      792,
      844
    ],
    [
      796,
      836,
      873,
      845
    ],
    [
      878,
      836,
      893,
      846
    ],
    [
      578,
      852,
      584,
      857
    ],
    [
      590,
      849,
      667,
      860
    ],
    [
      673,
      851,
      684,
      857
    ],
    [
      689,
      849,
      709,
      857
    ],
    [
      715,
      851,
      772,
      857
    ],
    [
      576,
      861,
      584,
      869
    ],
    [
      592,
      862,
      593,
      869
    ],
    [
      598,
      864,
      622,
      870
    ],
    [
      627,
      861,
      693,
      870
    ],
    [
      699,
      861,
      752,
      870
    ],
    [
      758,
      862,
      759,
      869
    ],
    [
      601,
      875,
      658,
      885
    ],
    [
      663,
      875,
      683,
      884
    ],
    [
      688,
      875,
      728,
      885
    ],
    [
      733,
      878,
      748,
      884
    ],
    [
      754,
      878,
      772,
      886
    ],
    [
      777,
      878,
      806,
      884
    ],
    [
      579,
      893,
      586,
      898
    ],
    [
      595,
      890,
      602,
      898
    ],
    [
      606,
      893,
      628,
      901
    ],
    [
      634,
      893,
      655,
      899
    ],
    [
      660,
      890,
      682,
      899
    ],
    [
      687,
      890,
      741,
      901
    ],
    [
      746,
      893,
      769,
      901
    ],
    [
      578,
      906,
      635,
      915
    ],
    [
      640,
      909,
      669,
      916
    ],
    [
      673,
      906,
      712,
      915
    ],
    [
      718,
      906,
      751,
      916
    ],
    [
      755,
      906,
      783,
      914
    ],
    [
      71,
      944,
      101,
      954
    ]
  ],
  "bboxes_pixel": [
    [
      174,
      87,
      550,
      141
    ],
    [
      572,
      88,
      731,
      140
    ],
    [
      759,
      87,
      885,
      141
    ],
    [
      912,
      87,
      1007,
      141
    ],
    [
      1034,
      87,
      1330,
      141
    ],
    [
      656,
      283,
      664,
      290
    ],
    [
      1301,
      264,
      1321,
      293
    ],
    [
      1363,
      265,
      1425,
      293
    ],
    [
      1439,
      265,
      1500,
      294
    ],
    [
      1516,
      265,
      1563,
      293
    ],
    [
      1577,
      275,
      1629,
      294
    ],
    [
      1644,
      265,
      1842,
      302
    ],
    [
      1858,
      267,
      1987,
      294
    ],
    [
      1999,
      265,
      2054,
      294
    ],
    [
      2067,
      270,
      2235,
      294
    ],
    [
      2247,
      265,
      2295,
      294
    ],
    [
      231,
      283,
      298,
      319
    ],
    [
      354,
      283,
      466,
      319
    ],
    [
      482,
      281,
      721,
      330
    ],
    [
      739,
      281,
      852,
      319
    ],
    [
      1401,
      314,
      1475,
      319
    ],
    [
      1363,
      312,
      1425,
      340
    ],
    [
      1439,
      312,
      1510,
      341
    ],
    [
      1525,
      312,
      1604,
      341
    ],
    [
      1616,
      312,
      1795,
      349
    ],
    [
      1809,
      312,
      1902,
      341
    ],
    [
      228,
      366,
      281,
      393
    ],
    [
      295,
      374,
      347,
      393
    ],
    [
      360,
      364,
      439,
      393
    ],
    [
      452,
      371,
      472,
      391
    ],
    [
      486,
      364,
      592,
      401
    ],
    [
      606,
      371,
      626,
      391
    ],
    [
      641,
      366,
      711,
      393
    ],
    [
      725,
      364,
      882,
      401
    ],
    [
      893,
      370,
      925,
      393
    ],
    [
      937,
      364,
      994,
      393
    ],
    [
      1005,
      364,
      1098,
      393
    ],
    [
      1109,
      364,
      1207,
      401
    ],
    [
      1367,
      372,
      1378,
      398
    ],
    [
      1407,
      370,
      1450,
      398
    ],
    [
      1464,
      376,
      1527,
      399
    ],
    [
      1540,
      370,
      1581,
      399
    ],
    [
      1594,
      381,
      1675,
      407
    ],
    [
      1687,
      373,
      1769,
      399
    ],
    [
      1783,
      381,
      1797,
      399
    ],
    [
      1810,
      370,
      1900,
      399
    ],
    [
      229,
      411,
      292,
      440
    ],
    [
      302,
      421,
      346,
      440
    ],
    [
      359,
      411,
      442,
      440
    ],
    [
      454,
      411,
      494,
      440
    ],
    [
      507,
      411,
      656,
      440
    ],
    [
      669,
      411,
      721,
      440
    ],
    [
      733,
      421,
      855,
      448
    ],
    [
      867,
      411,
      911,
      440
    ],
    [
      922,
      421,
      1071,
      440
    ],
    [
      1084,
      411,
      1145,
      440
    ],
    [
      1371,
      422,
      1429,
      450
    ],
    [
      230,
      458,
      347,
      495
    ],
    [
      359,
      468,
      374,
      487
    ],
    [
      388,
      458,
      590,
      495
    ],
    [
      602,
      464,
      634,
      487
    ],
    [
      647,
      458,
      687,
      487
    ],
    [
      699,
      458,
      743,
      487
    ],
    [
      756,
      468,
      796,
      487
    ],
    [
      1888,
      425,
      1971,
      451
    ],
    [
      1984,
      433,
      1998,
      451
    ],
    [
      2011,
      422,
      2101,
      451
    ],
    [
      1370,
      472,
      1387,
      498
    ],
    [
      1407,
      470,
      1487,
      499
    ],
    [
      1497,
      470,
      1548,
      499
    ],
    [
      1561,
      476,
      1649,
      499
    ],
    [
      1665,
      470,
      1716,
      499
    ],
    [
      1727,
      470,
      1811,
      499
    ],
    [
      1824,
      470,
      1867,
      498
    ],
    [
      1882,
      470,
      2015,
      507
    ],
    [
      2030,
      470,
      2070,
      499
    ],
    [
      2084,
      470,
      2154,
      499
    ],
    [
      1399,
      520,
      1477,
      549
    ],
    [
      1487,
      520,
      1537,
      549
    ],
    [
      1549,
      526,
      1637,
      549
    ],
    [
      1651,
      520,
      1702,
      549
    ],
    [
      1712,
      520,
      1795,
      549
    ],
    [
      1804,
      520,
      1861,
      548
    ],
    [
      2274,
      545,
      2278,
      548
    ],
    [
      1361,
      569,
      1378,
      595
    ],
    [
      1401,
      567,
      1444,
      595
    ],
    [
      1460,
      570,
      1480,
      596
    ],
    [
      1493,
      570,
      1584,
      604
    ],
    [
      1597,
      573,
      1628,
      596
    ],
    [
      1641,
      567,
      1758,
      604
    ],
    [
      1772,
      567,
      1813,
      596
    ],
    [
      1827,
      567,
      1903,
      596
    ],
    [
      1917,
      567,
      2048,
      596
    ],
    [
      2062,
      567,
      2093,
      596
    ],
    [
      2104,
      567,
      2262,
      604
    ],
    [
      1406,
      618,
      1430,
      643
    ],
    [
      1442,
      615,
      1493,
      644
    ],
    [
      1507,
      626,
      1582,
      644
    ],
    [
      251,
      659,
      370,
      685
    ],
    [
      475,
      659,
      532,
      685
    ],
    [
      540,
      667,
      595,
      692
    ],
    [
      607,
      658,
      710,
      692
    ],
    [
      722,
      658,
      772,
      685
    ],
    [
      784,
      658,
      861,
      685
    ],
    [
      873,
      658,
      1024,
      692
    ],
    [
      1414,
      654,
      1476,
      697
    ],
    [
      1944,
      665,
      2075,
      694
    ],
    [
      2088,
      665,
      2120,
      694
    ],
    [
      250,
      704,
      431,
      730
    ],
    [
      449,
      699,
      460,
      741
    ],
    [
      477,
      703,
      521,
      737
    ],
    [
      532,
      712,
      546,
      730
    ],
    [
      560,
      703,
      707,
      734
    ],
    [
      251,
      542,
      370,
      568
    ],
    [
      478,
      542,
      484,
      567
    ],
    [
      496,
      541,
      568,
      568
    ],
    [
      580,
      550,
      627,
      575
    ],
    [
      638,
      541,
      730,
      568
    ],
    [
      742,
      541,
      864,
      568
    ],
    [
      874,
      550,
      955,
      575
    ],
    [
      966,
      541,
      1062,
      575
    ],
    [
      250,
      582,
      357,
      624
    ],
    [
      477,
      586,
      521,
      620
    ],
    [
      532,
      595,
      546,
      613
    ],
    [
      560,
      585,
      737,
      622
    ],
    [
      750,
      586,
      866,
      617
    ],
    [
      1415,
      716,
      1573,
      753
    ],
    [
      1587,
      719,
      1611,
      744
    ],
    [
      1623,
      716,
      1674,
      745
    ],
    [
      1688,
      727,
      1763,
      745
    ],
    [
      251,
      776,
      317,
      802
    ],
    [
      329,
      775,
      436,
      809
    ],
    [
      479,
      776,
      525,
      802
    ],
    [
      537,
      775,
      595,
      802
    ],
    [
      606,
      775,
      656,
      802
    ],
    [
      668,
      775,
      780,
      802
    ],
    [
      792,
      775,
      920,
      809
    ],
    [
      1365,
      765,
      1385,
      791
    ],
    [
      1404,
      765,
      1440,
      792
    ],
    [
      1454,
      765,
      1487,
      792
    ],
    [
      1500,
      774,
      1564,
      792
    ],
    [
      1580,
      763,
      1623,
      791
    ],
    [
      1636,
      774,
      1694,
      792
    ],
    [
      1708,
      766,
      1838,
      800
    ],
    [
      1852,
      763,
      1893,
      792
    ],
    [
      1906,
      763,
      2017,
      800
    ],
    [
      2030,
      763,
      2098,
      792
    ],
    [
      477,
      820,
      521,
      854
    ],
    [
      532,
      829,
      546,
      847
    ],
    [
      560,
      819,
      737,
      856
    ],
    [
      751,
      821,
      863,
      856
    ],
    [
      1390,
      817,
      1426,
      844
    ],
    [
      1440,
      817,
      1473,
      844
    ],
    [
      1486,
      826,
      1550,
      844
    ],
    [
      1563,
      815,
      1620,
      843
    ],
    [
      1364,
      864,
      1381,
      890
    ],
    [
      1404,
      862,
      1447,
      890
    ],
    [
      1468,
      862,
      1510,
      891
    ],
    [
      1525,
      865,
      1581,
      899
    ],
    [
      1593,
      862,
      1714,
      899
    ],
    [
      1727,
      873,
      1813,
      891
    ],
    [
      1827,
      862,
      1916,
      899
    ],
    [
      1927,
      868,
      2014,
      891
    ],
    [
      1391,
      912,
      1453,
      957
    ],
    [
      2014,
      942,
      2018,
      945
    ],
    [
      1366,
      966,
      1385,
      992
    ],
    [
      1407,
      964,
      1450,
      992
    ],
    [
      1465,
      967,
      1485,
      993
    ],
    [
      1499,
      964,
      1628,
      1001
    ],
    [
      1642,
      975,
      1657,
      993
    ],
    [
      1669,
      970,
      1731,
      993
    ],
    [
      1746,
      964,
      1839,
      993
    ],
    [
      1851,
      964,
      1895,
      993
    ],
    [
      1908,
      964,
      1948,
      993
    ],
    [
      1961,
      964,
      2096,
      993
    ],
    [
      1400,
      1004,
      1458,
      1048
    ],
    [
      1880,
      1008,
      1924,
      1037
    ],
    [
      1937,
      1008,
      1977,
      1037
    ],
    [
      1990,
      1008,
      2126,
      1037
    ],
    [
      251,
      1055,
      370,
      1081
    ],
    [
      479,
      1054,
      550,
      1088
    ],
    [
      560,
      1054,
      633,
      1081
    ],
    [
      641,
      1056,
      697,
      1088
    ],
    [
      707,
      1054,
      765,
      1081
    ],
    [
      776,
      1063,
      792,
      1081
    ],
    [
      803,
      1054,
      875,
      1088
    ],
    [
      886,
      1054,
      1018,
      1081
    ],
    [
      1030,
      1056,
      1053,
      1080
    ],
    [
      1066,
      1054,
      1112,
      1081
    ],
    [
      1365,
      1057,
      1383,
      1083
    ],
    [
      1406,
      1055,
      1449,
      1083
    ],
    [
      1462,
      1055,
      1511,
      1083
    ],
    [
      1524,
      1055,
      1594,
      1084
    ],
    [
      1607,
      1055,
      1647,
      1084
    ],
    [
      1660,
      1055,
      1723,
      1092
    ],
    [
      1737,
      1058,
      1761,
      1083
    ],
    [
      1773,
      1055,
      1824,
      1084
    ],
    [
      1838,
      1055,
      2001,
      1084
    ],
    [
      251,
      1094,
      365,
      1137
    ],
    [
      477,
      1094,
      589,
      1137
    ],
    [
      1403,
      1113,
      1461,
      1141
    ],
    [
      477,
      1143,
      521,
      1177
    ],
    [
      532,
      1152,
      546,
      1170
    ],
    [
      560,
      1142,
      747,
      1179
    ],
    [
      251,
      893,
      317,
      919
    ],
    [
      478,
      893,
      537,
      919
    ],
    [
      548,
      892,
      624,
      919
    ],
    [
      634,
      892,
      700,
      919
    ],
    [
      711,
      901,
      769,
      919
    ],
    [
      781,
      892,
      883,
      926
    ],
    [
      896,
      892,
      937,
      919
    ],
    [
      949,
      892,
      1102,
      919
    ],
    [
      250,
      938,
      431,
      964
    ],
    [
      477,
      937,
      664,
      964
    ],
    [
      477,
      982,
      521,
      1016
    ],
    [
      532,
      991,
      546,
      1009
    ],
    [
      559,
      982,
      703,
      1018
    ],
    [
      1885,
      1116,
      1909,
      1141
    ],
    [
      1922,
      1113,
      1972,
      1142
    ],
    [
      1986,
      1113,
      2149,
      1142
    ],
    [
      1370,
      1162,
      1388,
      1188
    ],
    [
      1408,
      1162,
      1444,
      1189
    ],
    [
      1455,
      1162,
      1472,
      1188
    ],
    [
      1485,
      1171,
      1552,
      1197
    ],
    [
      1568,
      1160,
      1611,
      1188
    ],
    [
      1624,
      1171,
      1683,
      1189
    ],
    [
      1694,
      1160,
      1824,
      1197
    ],
    [
      1838,
      1160,
      1879,
      1189
    ],
    [
      1890,
      1160,
      2037,
      1189
    ],
    [
      247,
      1211,
      305,
      1255
    ],
    [
      479,
      1216,
      563,
      1243
    ],
    [
      575,
      1216,
      627,
      1242
    ],
    [
      639,
      1216,
      724,
      1243
    ],
    [
      736,
      1216,
      809,
      1243
    ],
    [
      821,
      1216,
      871,
      1243
    ],
    [
      882,
      1217,
      1027,
      1250
    ],
    [
      1039,
      1216,
      1117,
      1250
    ],
    [
      1128,
      1218,
      1151,
      1242
    ],
    [
      1164,
      1216,
      1213,
      1243
    ],
    [
      1421,
      1216,
      1457,
      1243
    ],
    [
      1468,
      1216,
      1485,
      1242
    ],
    [
      1498,
      1225,
      1565,
      1251
    ],
    [
      1578,
      1214,
      1636,
      1242
    ],
    [
      478,
      1260,
      540,
      1288
    ],
    [
      1368,
      1263,
      1387,
      1289
    ],
    [
      1409,
      1261,
      1452,
      1289
    ],
    [
      1467,
      1261,
      1565,
      1290
    ],
    [
      1579,
      1261,
      1619,
      1290
    ],
    [
      1632,
      1267,
      1748,
      1298
    ],
    [
      1761,
      1272,
      1837,
      1290
    ],
    [
      1851,
      1272,
      1865,
      1290
    ],
    [
      1880,
      1261,
      1990,
      1290
    ],
    [
      477,
      1305,
      520,
      1339
    ],
    [
      531,
      1314,
      545,
      1332
    ],
    [
      557,
      1305,
      697,
      1341
    ],
    [
      1395,
      1308,
      1456,
      1354
    ],
    [
      1885,
      1324,
      1962,
      1342
    ],
    [
      1975,
      1324,
      1990,
      1342
    ],
    [
      2004,
      1313,
      2114,
      1342
    ],
    [
      251,
      1378,
      290,
      1405
    ],
    [
      302,
      1379,
      394,
      1413
    ],
    [
      407,
      1382,
      439,
      1405
    ],
    [
      479,
      1378,
      563,
      1405
    ],
    [
      574,
      1387,
      623,
      1405
    ],
    [
      632,
      1387,
      688,
      1427
    ],
    [
      698,
      1379,
      789,
      1412
    ],
    [
      801,
      1382,
      833,
      1405
    ],
    [
      845,
      1378,
      917,
      1405
    ],
    [
      928,
      1387,
      943,
      1405
    ],
    [
      955,
      1387,
      1060,
      1412
    ],
    [
      1071,
      1378,
      1159,
      1405
    ],
    [
      1364,
      1386,
      1530,
      1423
    ],
    [
      1542,
      1386,
      1597,
      1415
    ],
    [
      1610,
      1391,
      1778,
      1415
    ],
    [
      1790,
      1386,
      1861,
      1415
    ],
    [
      1875,
      1386,
      1929,
      1415
    ],
    [
      1943,
      1391,
      2061,
      1415
    ],
    [
      2074,
      1386,
      2153,
      1415
    ],
    [
      2167,
      1386,
      2202,
      1415
    ],
    [
      2213,
      1386,
      2267,
      1415
    ],
    [
      477,
      1422,
      521,
      1456
    ],
    [
      533,
      1421,
      734,
      1458
    ],
    [
      1363,
      1433,
      1466,
      1462
    ],
    [
      1480,
      1435,
      1506,
      1461
    ],
    [
      1522,
      1433,
      1674,
      1462
    ],
    [
      1690,
      1435,
      1749,
      1462
    ],
    [
      1764,
      1433,
      1842,
      1462
    ],
    [
      1855,
      1433,
      2034,
      1470
    ],
    [
      2047,
      1433,
      2132,
      1462
    ],
    [
      2143,
      1433,
      2247,
      1462
    ],
    [
      1365,
      1490,
      1537,
      1517
    ],
    [
      232,
      1503,
      282,
      1530
    ],
    [
      295,
      1501,
      351,
      1529
    ],
    [
      363,
      1501,
      549,
      1530
    ],
    [
      562,
      1511,
      616,
      1530
    ],
    [
      626,
      1501,
      675,
      1530
    ],
    [
      686,
      1507,
      755,
      1530
    ],
    [
      763,
      1511,
      835,
      1538
    ],
    [
      849,
      1502,
      901,
      1535
    ],
    [
      913,
      1501,
      962,
      1529
    ],
    [
      976,
      1501,
      1017,
      1530
    ],
    [
      1031,
      1504,
      1048,
      1530
    ],
    [
      1060,
      1501,
      1218,
      1535
    ],
    [
      1367,
      1547,
      1378,
      1573
    ],
    [
      1398,
      1555,
      1414,
      1573
    ],
    [
      1436,
      1546,
      1527,
      1574
    ],
    [
      1542,
      1548,
      1562,
      1574
    ],
    [
      1575,
      1556,
      1590,
      1574
    ],
    [
      1604,
      1545,
      1787,
      1574
    ],
    [
      1802,
      1545,
      1859,
      1574
    ],
    [
      1436,
      1591,
      1643,
      1628
    ],
    [
      1657,
      1591,
      1722,
      1624
    ],
    [
      1734,
      1591,
      1778,
      1620
    ],
    [
      1790,
      1602,
      1905,
      1628
    ],
    [
      1399,
      1640,
      1418,
      1668
    ],
    [
      1437,
      1642,
      1481,
      1668
    ],
    [
      1496,
      1640,
      1584,
      1669
    ],
    [
      1596,
      1651,
      1652,
      1677
    ],
    [
      1666,
      1642,
      1740,
      1669
    ],
    [
      1752,
      1651,
      1805,
      1669
    ],
    [
      1817,
      1642,
      1893,
      1669
    ],
    [
      1906,
      1646,
      1961,
      1677
    ],
    [
      1976,
      1640,
      2054,
      1669
    ],
    [
      2068,
      1643,
      2092,
      1668
    ],
    [
      2107,
      1640,
      2157,
      1669
    ],
    [
      2169,
      1651,
      2250,
      1669
    ],
    [
      232,
      1561,
      282,
      1588
    ],
    [
      295,
      1559,
      345,
      1587
    ],
    [
      356,
      1559,
      434,
      1588
    ],
    [
      448,
      1569,
      505,
      1588
    ],
    [
      516,
      1559,
      571,
      1588
    ],
    [
      583,
      1559,
      793,
      1588
    ],
    [
      804,
      1565,
      873,
      1588
    ],
    [
      881,
      1569,
      953,
      1596
    ],
    [
      967,
      1559,
      1014,
      1596
    ],
    [
      1025,
      1559,
      1196,
      1596
    ],
    [
      228,
      1620,
      281,
      1647
    ],
    [
      294,
      1628,
      346,
      1647
    ],
    [
      361,
      1628,
      413,
      1647
    ],
    [
      426,
      1623,
      485,
      1655
    ],
    [
      495,
      1618,
      609,
      1647
    ],
    [
      623,
      1618,
      654,
      1647
    ],
    [
      666,
      1618,
      746,
      1647
    ],
    [
      232,
      1678,
      282,
      1705
    ],
    [
      295,
      1676,
      357,
      1705
    ],
    [
      368,
      1686,
      434,
      1705
    ],
    [
      444,
      1676,
      582,
      1705
    ],
    [
      594,
      1676,
      685,
      1705
    ],
    [
      701,
      1689,
      720,
      1697
    ],
    [
      734,
      1678,
      784,
      1705
    ],
    [
      796,
      1681,
      856,
      1713
    ],
    [
      867,
      1686,
      932,
      1705
    ],
    [
      943,
      1676,
      1080,
      1705
    ],
    [
      1092,
      1676,
      1183,
      1705
    ],
    [
      1434,
      1693,
      1498,
      1722
    ],
    [
      1513,
      1693,
      1563,
      1722
    ],
    [
      1576,
      1693,
      1752,
      1722
    ],
    [
      1761,
      1711,
      1780,
      1713
    ],
    [
      1791,
      1693,
      1844,
      1722
    ],
    [
      1436,
      1740,
      1583,
      1777
    ],
    [
      1596,
      1740,
      1670,
      1774
    ],
    [
      1388,
      1803,
      1403,
      1821
    ],
    [
      1423,
      1793,
      1516,
      1822
    ],
    [
      1519,
      1789,
      1531,
      1834
    ],
    [
      1547,
      1804,
      1606,
      1822
    ],
    [
      1609,
      1789,
      1621,
      1834
    ],
    [
      1648,
      1793,
      1715,
      1822
    ],
    [
      1729,
      1793,
      1781,
      1826
    ],
    [
      1797,
      1795,
      1800,
      1821
    ],
    [
      1815,
      1804,
      1891,
      1822
    ],
    [
      1436,
      1839,
      1555,
      1875
    ],
    [
      1568,
      1838,
      1633,
      1871
    ],
    [
      1647,
      1838,
      1755,
      1875
    ],
    [
      208,
      1809,
      221,
      1838
    ],
    [
      270,
      1810,
      436,
      1847
    ],
    [
      448,
      1810,
      503,
      1839
    ],
    [
      516,
      1815,
      684,
      1839
    ],
    [
      696,
      1810,
      767,
      1839
    ],
    [
      781,
      1810,
      835,
      1839
    ],
    [
      849,
      1815,
      967,
      1839
    ],
    [
      979,
      1810,
      1059,
      1839
    ],
    [
      1073,
      1810,
      1108,
      1839
    ],
    [
      1120,
      1810,
      1207,
      1839
    ],
    [
      273,
      1877,
      284,
      1903
    ],
    [
      313,
      1877,
      373,
      1904
    ],
    [
      384,
      1875,
      529,
      1904
    ],
    [
      544,
      1877,
      547,
      1903
    ],
    [
      803,
      1886,
      847,
      1912
    ],
    [
      860,
      1875,
      925,
      1904
    ],
    [
      939,
      1875,
      1081,
      1912
    ],
    [
      1094,
      1886,
      1128,
      1904
    ],
    [
      1366,
      1893,
      1384,
      1919
    ],
    [
      1398,
      1901,
      1414,
      1919
    ],
    [
      1437,
      1893,
      1545,
      1920
    ],
    [
      1559,
      1902,
      1615,
      1924
    ],
    [
      1629,
      1891,
      1716,
      1920
    ],
    [
      1728,
      1902,
      1784,
      1928
    ],
    [
      313,
      1928,
      315,
      1954
    ],
    [
      330,
      1926,
      460,
      1955
    ],
    [
      473,
      1937,
      513,
      1963
    ],
    [
      525,
      1926,
      569,
      1955
    ],
    [
      581,
      1937,
      595,
      1955
    ],
    [
      610,
      1926,
      675,
      1955
    ],
    [
      689,
      1926,
      756,
      1955
    ],
    [
      1454,
      1938,
      1561,
      1972
    ],
    [
      1575,
      1938,
      1679,
      1975
    ],
    [
      1692,
      1938,
      1724,
      1967
    ],
    [
      1735,
      1949,
      1775,
      1971
    ],
    [
      1790,
      1938,
      1910,
      1975
    ],
    [
      272,
      1981,
      344,
      2007
    ],
    [
      598,
      1990,
      653,
      2016
    ],
    [
      906,
      1990,
      977,
      2016
    ],
    [
      987,
      1979,
      1127,
      2016
    ],
    [
      1407,
      1991,
      1426,
      2019
    ],
    [
      1444,
      1993,
      1447,
      2019
    ],
    [
      1463,
      1991,
      1541,
      2020
    ],
    [
      1553,
      1997,
      1585,
      2020
    ],
    [
      1984,
      1991,
      2090,
      2024
    ],
    [
      2105,
      1991,
      2208,
      2028
    ],
    [
      311,
      2033,
      487,
      2070
    ],
    [
      1434,
      2039,
      1478,
      2068
    ],
    [
      1491,
      2050,
      1536,
      2076
    ],
    [
      1548,
      2050,
      1612,
      2068
    ],
    [
      1624,
      2045,
      1770,
      2076
    ],
    [
      312,
      2088,
      341,
      2114
    ],
    [
      354,
      2088,
      415,
      2119
    ],
    [
      428,
      2097,
      472,
      2115
    ],
    [
      485,
      2097,
      540,
      2115
    ],
    [
      553,
      2088,
      647,
      2115
    ],
    [
      658,
      2092,
      712,
      2115
    ],
    [
      726,
      2086,
      798,
      2123
    ],
    [
      809,
      2092,
      840,
      2115
    ],
    [
      854,
      2086,
      894,
      2115
    ],
    [
      908,
      2089,
      926,
      2115
    ],
    [
      938,
      2097,
      975,
      2115
    ],
    [
      989,
      2097,
      1042,
      2115
    ],
    [
      1053,
      2097,
      1126,
      2115
    ],
    [
      1399,
      2098,
      1414,
      2116
    ],
    [
      1434,
      2090,
      1491,
      2117
    ],
    [
      1506,
      2088,
      1578,
      2117
    ],
    [
      1590,
      2094,
      1621,
      2117
    ],
    [
      1635,
      2099,
      1691,
      2125
    ],
    [
      1701,
      2094,
      1751,
      2117
    ],
    [
      1765,
      2099,
      1851,
      2117
    ],
    [
      1865,
      2088,
      1883,
      2116
    ],
    [
      1892,
      2099,
      1948,
      2125
    ],
    [
      1961,
      2094,
      2037,
      2117
    ],
    [
      2047,
      2094,
      2079,
      2117
    ],
    [
      272,
      2141,
      289,
      2167
    ],
    [
      310,
      2141,
      386,
      2168
    ],
    [
      399,
      2139,
      509,
      2176
    ],
    [
      523,
      2142,
      543,
      2168
    ],
    [
      556,
      2139,
      655,
      2176
    ],
    [
      665,
      2150,
      747,
      2176
    ],
    [
      760,
      2139,
      809,
      2168
    ],
    [
      823,
      2139,
      880,
      2168
    ],
    [
      894,
      2139,
      947,
      2168
    ],
    [
      960,
      2139,
      1078,
      2168
    ],
    [
      1090,
      2139,
      1167,
      2168
    ],
    [
      1849,
      2141,
      2061,
      2178
    ],
    [
      2075,
      2141,
      2167,
      2170
    ],
    [
      2179,
      2141,
      2230,
      2170
    ],
    [
      311,
      2203,
      364,
      2229
    ],
    [
      377,
      2203,
      466,
      2221
    ],
    [
      481,
      2192,
      538,
      2221
    ],
    [
      793,
      2192,
      842,
      2221
    ],
    [
      855,
      2192,
      946,
      2221
    ],
    [
      959,
      2192,
      1107,
      2221
    ],
    [
      1436,
      2198,
      1579,
      2216
    ],
    [
      310,
      2255,
      395,
      2281
    ],
    [
      407,
      2244,
      470,
      2281
    ],
    [
      1366,
      2238,
      1384,
      2264
    ],
    [
      1398,
      2246,
      1414,
      2264
    ],
    [
      1437,
      2238,
      1481,
      2264
    ],
    [
      1496,
      2239,
      1579,
      2273
    ],
    [
      1593,
      2236,
      1690,
      2273
    ],
    [
      1701,
      2242,
      1848,
      2273
    ],
    [
      1858,
      2236,
      1913,
      2265
    ],
    [
      1925,
      2236,
      2008,
      2265
    ],
    [
      2020,
      2236,
      2152,
      2265
    ],
    [
      2166,
      2247,
      2211,
      2273
    ],
    [
      2223,
      2247,
      2269,
      2265
    ],
    [
      271,
      2300,
      290,
      2326
    ],
    [
      309,
      2298,
      369,
      2327
    ],
    [
      381,
      2298,
      519,
      2327
    ],
    [
      534,
      2298,
      600,
      2327
    ],
    [
      612,
      2298,
      695,
      2335
    ],
    [
      707,
      2298,
      796,
      2335
    ],
    [
      1052,
      2309,
      1107,
      2335
    ],
    [
      1436,
      2292,
      1457,
      2318
    ],
    [
      1470,
      2295,
      1498,
      2318
    ],
    [
      1509,
      2289,
      1560,
      2318
    ],
    [
      1573,
      2289,
      1758,
      2318
    ],
    [
      1774,
      2291,
      1777,
      2317
    ],
    [
      1436,
      2337,
      1588,
      2373
    ],
    [
      550,
      2351,
      631,
      2380
    ],
    [
      645,
      2351,
      770,
      2380
    ],
    [
      784,
      2351,
      925,
      2388
    ],
    [
      1388,
      2389,
      1407,
      2417
    ],
    [
      1423,
      2391,
      1520,
      2418
    ],
    [
      1533,
      2400,
      1548,
      2418
    ],
    [
      1562,
      2389,
      1722,
      2418
    ],
    [
      1738,
      2391,
      1779,
      2418
    ],
    [
      1436,
      2437,
      1632,
      2473
    ],
    [
      272,
      2405,
      289,
      2431
    ],
    [
      309,
      2405,
      344,
      2431
    ],
    [
      356,
      2403,
      461,
      2432
    ],
    [
      475,
      2403,
      524,
      2432
    ],
    [
      536,
      2414,
      592,
      2440
    ],
    [
      607,
      2403,
      664,
      2440
    ],
    [
      674,
      2414,
      745,
      2440
    ],
    [
      757,
      2414,
      820,
      2432
    ],
    [
      831,
      2403,
      960,
      2432
    ],
    [
      973,
      2403,
      1125,
      2432
    ],
    [
      299,
      2460,
      329,
      2486
    ],
    [
      344,
      2460,
      347,
      2486
    ],
    [
      615,
      2459,
      633,
      2485
    ],
    [
      645,
      2456,
      793,
      2493
    ],
    [
      807,
      2456,
      865,
      2485
    ],
    [
      879,
      2456,
      968,
      2485
    ],
    [
      981,
      2456,
      1018,
      2493
    ],
    [
      1030,
      2467,
      1045,
      2485
    ],
    [
      1058,
      2462,
      1216,
      2493
    ],
    [
      2058,
      2492,
      2062,
      2495
    ],
    [
      1388,
      2499,
      1403,
      2517
    ],
    [
      1423,
      2491,
      1476,
      2518
    ],
    [
      1489,
      2500,
      1541,
      2518
    ],
    [
      1974,
      2490,
      2161,
      2526
    ],
    [
      2173,
      2490,
      2227,
      2523
    ],
    [
      1436,
      2540,
      1464,
      2563
    ],
    [
      1476,
      2545,
      1528,
      2563
    ],
    [
      1540,
      2545,
      1660,
      2571
    ],
    [
      1676,
      2536,
      1750,
      2563
    ],
    [
      1764,
      2545,
      1811,
      2563
    ],
    [
      1825,
      2545,
      1877,
      2563
    ],
    [
      1889,
      2537,
      1990,
      2571
    ],
    [
      272,
      2511,
      290,
      2537
    ],
    [
      313,
      2511,
      342,
      2537
    ],
    [
      356,
      2509,
      474,
      2538
    ],
    [
      488,
      2510,
      576,
      2546
    ],
    [
      591,
      2520,
      643,
      2538
    ],
    [
      659,
      2511,
      661,
      2537
    ],
    [
      676,
      2509,
      725,
      2538
    ],
    [
      739,
      2520,
      794,
      2546
    ],
    [
      809,
      2509,
      883,
      2538
    ],
    [
      896,
      2509,
      981,
      2538
    ],
    [
      313,
      2563,
      315,
      2589
    ],
    [
      566,
      2572,
      591,
      2589
    ],
    [
      645,
      2564,
      741,
      2590
    ],
    [
      776,
      2561,
      874,
      2590
    ],
    [
      888,
      2567,
      916,
      2590
    ],
    [
      927,
      2561,
      978,
      2590
    ],
    [
      992,
      2567,
      1133,
      2590
    ],
    [
      1520,
      2590,
      1523,
      2593
    ],
    [
      328,
      2572,
      641,
      2598
    ],
    [
      753,
      2572,
      772,
      2598
    ],
    [
      1365,
      2589,
      1414,
      2615
    ],
    [
      1434,
      2589,
      1540,
      2616
    ],
    [
      1553,
      2598,
      1568,
      2616
    ],
    [
      1580,
      2587,
      1666,
      2616
    ],
    [
      1681,
      2593,
      1780,
      2624
    ],
    [
      1796,
      2589,
      1837,
      2616
    ],
    [
      1491,
      2634,
      1737,
      2671
    ],
    [
      1749,
      2634,
      1793,
      2663
    ],
    [
      1804,
      2634,
      1889,
      2663
    ],
    [
      1901,
      2634,
      2021,
      2671
    ],
    [
      272,
      2616,
      289,
      2642
    ],
    [
      313,
      2616,
      315,
      2642
    ],
    [
      329,
      2614,
      407,
      2643
    ],
    [
      420,
      2616,
      458,
      2643
    ],
    [
      471,
      2614,
      538,
      2643
    ],
    [
      551,
      2614,
      569,
      2642
    ],
    [
      578,
      2625,
      622,
      2643
    ],
    [
      636,
      2620,
      717,
      2643
    ],
    [
      729,
      2620,
      758,
      2643
    ],
    [
      769,
      2625,
      839,
      2651
    ],
    [
      851,
      2614,
      944,
      2651
    ],
    [
      956,
      2616,
      1009,
      2643
    ],
    [
      545,
      2668,
      596,
      2697
    ],
    [
      610,
      2668,
      765,
      2697
    ],
    [
      780,
      2668,
      976,
      2697
    ],
    [
      990,
      2668,
      1047,
      2697
    ],
    [
      1060,
      2668,
      1168,
      2697
    ],
    [
      1401,
      2686,
      1420,
      2714
    ],
    [
      1438,
      2688,
      1499,
      2715
    ],
    [
      1510,
      2697,
      1585,
      2723
    ],
    [
      1598,
      2697,
      1642,
      2715
    ],
    [
      2069,
      2686,
      2227,
      2719
    ],
    [
      1452,
      2735,
      1575,
      2772
    ],
    [
      1589,
      2735,
      1625,
      2772
    ],
    [
      1637,
      2746,
      1652,
      2764
    ],
    [
      1664,
      2735,
      1750,
      2764
    ],
    [
      1765,
      2741,
      1864,
      2772
    ],
    [
      311,
      2721,
      379,
      2750
    ],
    [
      391,
      2721,
      581,
      2758
    ],
    [
      272,
      2776,
      290,
      2802
    ],
    [
      311,
      2774,
      351,
      2803
    ],
    [
      362,
      2785,
      466,
      2803
    ],
    [
      480,
      2774,
      659,
      2803
    ],
    [
      671,
      2774,
      754,
      2803
    ],
    [
      765,
      2785,
      824,
      2803
    ],
    [
      836,
      2776,
      1006,
      2811
    ],
    [
      1023,
      2774,
      1080,
      2803
    ],
    [
      1397,
      2798,
      1413,
      2816
    ],
    [
      1435,
      2790,
      1479,
      2816
    ],
    [
      1494,
      2788,
      1590,
      2817
    ],
    [
      1604,
      2788,
      1677,
      2825
    ],
    [
      1690,
      2799,
      1754,
      2817
    ],
    [
      1767,
      2788,
      1824,
      2817
    ],
    [
      1839,
      2790,
      1842,
      2816
    ],
    [
      552,
      2829,
      570,
      2855
    ],
    [
      583,
      2826,
      671,
      2855
    ],
    [
      684,
      2826,
      820,
      2863
    ],
    [
      831,
      2826,
      875,
      2855
    ],
    [
      885,
      2826,
      936,
      2855
    ],
    [
      949,
      2832,
      1036,
      2863
    ],
    [
      1436,
      2834,
      1588,
      2871
    ],
    [
      1601,
      2834,
      1732,
      2871
    ],
    [
      1366,
      2883,
      1384,
      2909
    ],
    [
      1398,
      2891,
      1414,
      2909
    ],
    [
      1434,
      2881,
      1530,
      2910
    ],
    [
      1542,
      2881,
      1671,
      2910
    ],
    [
      1684,
      2881,
      1772,
      2910
    ],
    [
      1786,
      2881,
      1853,
      2910
    ],
    [
      1864,
      2881,
      1922,
      2910
    ],
    [
      1937,
      2883,
      2016,
      2910
    ],
    [
      1879,
      2934,
      1919,
      2967
    ],
    [
      1934,
      2934,
      1965,
      2963
    ],
    [
      1975,
      2934,
      2166,
      2967
    ],
    [
      2180,
      2934,
      2216,
      2971
    ],
    [
      1436,
      2992,
      1450,
      3010
    ],
    [
      1465,
      2981,
      1656,
      3018
    ],
    [
      1671,
      2987,
      1699,
      3010
    ],
    [
      1710,
      2981,
      1761,
      3010
    ],
    [
      1774,
      2987,
      1916,
      3010
    ],
    [
      1431,
      3024,
      1450,
      3052
    ],
    [
      1469,
      3026,
      1472,
      3052
    ],
    [
      1485,
      3035,
      1544,
      3053
    ],
    [
      1557,
      3024,
      1721,
      3053
    ],
    [
      1735,
      3024,
      1866,
      3053
    ],
    [
      1881,
      3026,
      1884,
      3052
    ],
    [
      1492,
      3073,
      1633,
      3107
    ],
    [
      1646,
      3073,
      1697,
      3102
    ],
    [
      1709,
      3073,
      1807,
      3106
    ],
    [
      1820,
      3084,
      1858,
      3102
    ],
    [
      1872,
      3084,
      1917,
      3110
    ],
    [
      1929,
      3084,
      2002,
      3102
    ],
    [
      1438,
      3136,
      1454,
      3154
    ],
    [
      1477,
      3126,
      1494,
      3154
    ],
    [
      1504,
      3137,
      1560,
      3163
    ],
    [
      1574,
      3137,
      1626,
      3155
    ],
    [
      1638,
      3126,
      1693,
      3155
    ],
    [
      1706,
      3126,
      1840,
      3163
    ],
    [
      1853,
      3137,
      1908,
      3163
    ],
    [
      1436,
      3180,
      1576,
      3214
    ],
    [
      1590,
      3191,
      1660,
      3217
    ],
    [
      1671,
      3180,
      1768,
      3214
    ],
    [
      1782,
      3180,
      1864,
      3217
    ],
    [
      1875,
      3180,
      1945,
      3209
    ],
    [
      177,
      3316,
      252,
      3349
    ]
  ]
}